loadstar_sensors_interface/__about__.py
loadstar_sensors_interface/__init__.py
loadstar_sensors_interface/cli.py
loadstar_sensors_interface/loadstar_sensors_interface.py
loadstar_sensors_interface-2.1.1.dist-info/LICENSE
loadstar_sensors_interface-2.1.1.dist-info/METADATA
loadstar_sensors_interface-2.1.1.dist-info/WHEEL
loadstar_sensors_interface-2.1.1.dist-info/entry_points.txt
loadstar_sensors_interface-2.1.1.dist-info/top_level.txt
loadstar_sensors_interface-2.1.1.dist-info/RECORD
