Metadata-Version: 2.1
Name: loadstar-sensors-interface
Version: 2.1.1
Summary: Python async interface to Loadstar Sensors USB devices.
Home-page: https://github.com/janelia-pypi/loadstar_sensors_interface_python
Author: Peter Polidoro
Author-email: peter@polidoro.io
License: BSD-3-Clause
Platform: UNKNOWN
Classifier: Programming Language :: Python :: 3
License-File: LICENSE
Requires-Dist: pyserial-asyncio
Requires-Dist: pint
Requires-Dist: click
